wasmstore/__init__.py
wasmstore/wasmstore.py
wasmstore-0.3.0.dist-info/LICENSE
wasmstore-0.3.0.dist-info/METADATA
wasmstore-0.3.0.dist-info/WHEEL
wasmstore-0.3.0.dist-info/RECORD
