Metadata-Version: 2.1
Name: wasmstore
Version: 0.3.0
Summary: Wasmstore client for Python
License: BSD-3-Clause
Author: Dylibso
Author-email: oss@dylib.so
Requires-Python: >=3.9,<4.0
Classifier: License :: OSI Approved :: BSD License
Classifier: Programming Language :: Python :: 3
Classifier: Programming Language :: Python :: 3.9
Classifier: Programming Language :: Python :: 3.10
Classifier: Programming Language :: Python :: 3.11
Classifier: Programming Language :: Python :: 3.12
Requires-Dist: requests (>=2.28.1,<3.0.0)
